csv2vcard/__init__.py
csv2vcard/create_vcard.py
csv2vcard/csv2vcard.py
csv2vcard/export_vcard.py
csv2vcard/parse_csv.py
csvTovcf-0.3.0.dist-info/DESCRIPTION.rst
csvTovcf-0.3.0.dist-info/METADATA
csvTovcf-0.3.0.dist-info/RECORD
csvTovcf-0.3.0.dist-info/WHEEL
csvTovcf-0.3.0.dist-info/metadata.json
csvTovcf-0.3.0.dist-info/top_level.txt
