Metadata-Version: 2.0
Name: csvTovcf
Version: 0.3.0
Summary: A library for converting csv to .vcf file
Home-page: https://github.com/stripathi669/csv2vcard
Author: Shivam Mani Tripathi
Author-email: abc@privatemail.com
License: UNKNOWN
Download-URL: https://github.com/stripathi669/csv2vcard/archive/0.3.0.tar.gz
Keywords: csv,vcard,export,vcf
Platform: UNKNOWN
Classifier: Development Status :: 3 - Alpha
Classifier: License :: OSI Approved :: MIT License
Classifier: Programming Language :: Python :: 3.6
Requires-Python: >=3.6
